Search_Scrape/__init__.py
Search_Scrape/main.py
Search_Scrape-1.0.2.dist-info/LICENSE
Search_Scrape-1.0.2.dist-info/METADATA
Search_Scrape-1.0.2.dist-info/WHEEL
Search_Scrape-1.0.2.dist-info/top_level.txt
Search_Scrape-1.0.2.dist-info/RECORD
