Metadata-Version: 2.1
Name: Search-Scrape
Version: 1.0.2
License-File: LICENSE
Requires-Dist: beautifulsoup4
Requires-Dist: requests
